api/__init__.py
api/database_endpoint.py
api/search_endpoint.py
clea_vectordb-0.1.0.dist-info/licenses/LICENSE
vectordb/__init__.py
vectordb/database.py
vectordb/embeddings.py
vectordb/ranking.py
vectordb/search.py
clea_vectordb-0.1.0.dist-info/METADATA
clea_vectordb-0.1.0.dist-info/WHEEL
clea_vectordb-0.1.0.dist-info/entry_points.txt
clea_vectordb-0.1.0.dist-info/top_level.txt
clea_vectordb-0.1.0.dist-info/RECORD
