Metadata-Version: 2.4
Name: clea-vectordb
Version: 0.1.0
Summary: Cléa-VectorDB: A hybrid search engine combining vector and metadata-based search. CRUD operations are performed using FastAPI.
Author-email: William <pikachu0442@gmail.com>
License-Expression: MIT
Project-URL: Homepage, https://github.com/WillIsback/Clea-VectorDB
Project-URL: Documentation, https://github.com/WillIsback/Clea-VectorDB#readme
Project-URL: Repository, https://github.com/WillIsback/Clea-VectorDB
Keywords: vector search,FastAPI,SvelteKit,pgvector,hybrid search
Classifier: Development Status :: 4 - Beta
Classifier: Intended Audience :: Developers
Classifier: Topic :: Software Development :: Libraries
Classifier: Programming Language :: Python :: 3
Classifier: Programming Language :: Python :: 3.11
Requires-Python: >=3.11
License-File: LICENSE
Requires-Dist: fastapi[standard]>=0.95.0
Requires-Dist: uvicorn>=0.22.0
Requires-Dist: sqlalchemy>=1.4.0
Requires-Dist: psycopg2>=2.9.0
Requires-Dist: pgvector>=0.1.0
Requires-Dist: transformers>=4.0.0
Requires-Dist: sentence-transformers>=2.2.2
Requires-Dist: numpy>=1.21.0
Requires-Dist: scipy>=1.7.0
Requires-Dist: pydantic>=1.10.0
Requires-Dist: ruff>=0.11.7
Provides-Extra: dev
Requires-Dist: pytest>=7.0; extra == "dev"
Requires-Dist: pytest-asyncio>=0.20.0; extra == "dev"
Requires-Dist: ruff>=0.11.7; extra == "dev"
Dynamic: license-file
